smart_mouse/__init__.py
smart_mouse/core.py
smart_mouse/mousedata.json
smart_mouse-1.0.5.dist-info/licenses/LICENSE
smart_mouse-1.0.5.dist-info/METADATA
smart_mouse-1.0.5.dist-info/WHEEL
smart_mouse-1.0.5.dist-info/top_level.txt
smart_mouse-1.0.5.dist-info/RECORD
