Metadata-Version: 2.4
Name: smart-mouse
Version: 1.0.5
Summary: Human-like mouse movement simulation using recorded patterns
Home-page: https://github.com/Bandit-HaxUnit/humanmouse
Author: HumanMouse Team
Author-email: HumanMouse Team <contact@humanmouse.com>
License: MIT
Project-URL: Homepage, https://github.com/Bandit-HaxUnit/humanmouse
Project-URL: Bug Tracker, https://github.com/Bandit-HaxUnit/humanmouse/issues
Project-URL: Documentation, https://github.com/Bandit-HaxUnit/humanmouse#readme
Project-URL: Source Code, https://github.com/Bandit-HaxUnit/humanmouse
Keywords: mouse,movement,automation,human-like,simulation,robotics,ui,testing
Classifier: Development Status :: 4 - Beta
Classifier: Intended Audience :: Developers
Classifier: Topic :: Software Development :: Libraries :: Python Modules
Classifier: Topic :: System :: Operating System
Classifier: Topic :: Desktop Environment
Classifier: License :: OSI Approved :: MIT License
Classifier: Programming Language :: Python :: 3
Classifier: Programming Language :: Python :: 3.7
Classifier: Programming Language :: Python :: 3.8
Classifier: Programming Language :: Python :: 3.9
Classifier: Programming Language :: Python :: 3.10
Classifier: Programming Language :: Python :: 3.11
Classifier: Programming Language :: Python :: 3.12
Classifier: Operating System :: OS Independent
Requires-Python: >=3.7
License-File: LICENSE
Requires-Dist: pynput>=1.7.0
Provides-Extra: dev
Requires-Dist: pytest>=6.0; extra == "dev"
Requires-Dist: pytest-cov>=2.0; extra == "dev"
Requires-Dist: black>=21.0; extra == "dev"
Requires-Dist: flake8>=3.8; extra == "dev"
Requires-Dist: mypy>=0.910; extra == "dev"
Requires-Dist: build>=0.7.0; extra == "dev"
Requires-Dist: twine>=3.4.0; extra == "dev"
Provides-Extra: test
Requires-Dist: pytest>=6.0; extra == "test"
Requires-Dist: pytest-cov>=2.0; extra == "test"
Dynamic: author
Dynamic: home-page
Dynamic: license-file
Dynamic: requires-python
